usrr16/__init__.py
usrr16/usrr16.py
usrr16-0.0.2.dist-info/LICENSE
usrr16-0.0.2.dist-info/METADATA
usrr16-0.0.2.dist-info/WHEEL
usrr16-0.0.2.dist-info/top_level.txt
usrr16-0.0.2.dist-info/RECORD
