Metadata-Version: 2.1
Name: usrr16
Version: 0.0.2
Summary: USR-R16 / USR-R16-T controller
Home-page: https://github.com/v1a0/usr-r16
Download-URL: https://github.com/V1A0/usr-r16/archive/refs/tags/v0.0.2.tar.gz
Author: v1a0
Author-email: contact@v1a0.dev
License: gpl-3.0
Keywords: relay,usr-r16,usr-r16-t,usrr16,usrr16t,lonhand,api
Platform: UNKNOWN
Classifier: Development Status :: 3 - Alpha
Classifier: Intended Audience :: Developers
Classifier: Topic :: Software Development :: Build Tools
Classifier: License :: OSI Approved :: GNU General Public License v3 (GPLv3)
Classifier: Programming Language :: Python :: 3.9
License-File: LICENSE
